blackduck/__init__.py
blackduck/__main__.py
blackduck/game.py
blackduck_game-0.3.0.dist-info/licenses/LICENSE
blackduck_game-0.3.0.dist-info/METADATA
blackduck_game-0.3.0.dist-info/WHEEL
blackduck_game-0.3.0.dist-info/entry_points.txt
blackduck_game-0.3.0.dist-info/top_level.txt
blackduck_game-0.3.0.dist-info/RECORD
