Metadata-Version: 2.4
Name: blackduck-game
Version: 0.3.0
Summary: Blackjack but with ducks. And for some reason, a complex ATM system
Author-email: Braeden Sy Tan <braedenjairsytan@icloud.com>
License-Expression: GPL-3.0-only
Project-URL: Homepage, https://github.com/DuckyBoi-XD/BlackJack-Ducky
Keywords: blackjack,game,card-game,casino,duck
Classifier: Development Status :: 4 - Beta
Classifier: Intended Audience :: End Users/Desktop
Classifier: Operating System :: OS Independent
Classifier: Programming Language :: Python :: 3
Classifier: Programming Language :: Python :: 3.8
Classifier: Programming Language :: Python :: 3.9
Classifier: Programming Language :: Python :: 3.10
Classifier: Programming Language :: Python :: 3.11
Classifier: Programming Language :: Python :: 3.12
Classifier: Programming Language :: Python :: 3.13
Classifier: Topic :: Games/Entertainment :: Board Games
Requires-Python: >=3.8
License-File: LICENSE
Dynamic: license-file
